{"Gradients_by_loss recover_latent/: encoder12":0.0020022169705448327,"Gradients_by_loss rec_from_latent_pretrain/: encoder10":0,"Gradients_by_loss rec_from_latent_pretrain/: encoder7":0,"Gradients_by_loss recover_latent/: mapper13":0.009171547364622196,"Gradients_by_loss rec_from_latent_pretrain/: mapper8":0,"Gradients_by_loss rec_from_latent_pretrain/: mapper3":0,"Gradients_by_loss rec_from_latent_pretrain/: mapper5":0,"Gradients_by_loss recover_latent/: decoder":0,"Gradients_by_loss rec_from_latent_pretrain/: encoder5":0,"Gradients_by_loss recover_latent/: encoder1":0.002784656509760138,"Gradients_by_loss rec_from_latent_pretrain/: decoder":0.05741890566562805,"_wandb":{"runtime":187},"Gradients_by_loss rec_from_latent_pretrain/: mapper7":0,"Gradients_by_loss rec_from_latent_pretrain/: mapper11":0,"Gradients_by_loss recover_latent/: encoder14":0.0017708393027542843,"Gradients_by_loss rec_from_latent_pretrain/: encoder13":0,"Gradients_by_loss rec_from_latent_pretrain/: encoder_pretrain":0.02504590507617431,"Gradients_by_loss recover_latent/: encoder0":0.00614789825888367,"Gradients_by_loss rec_from_latent_pretrain/: mapper4":0,"Gradients_by_loss recover_latent/: px_r":0,"Gradients_by_loss rec_from_latent_pretrain/: px_r":0.002906567184254527,"Gradients_by_loss recover_latent/: mapper2":0.00636343763162132,"Gradients_by_loss rec_from_latent_pretrain/: mapper1":0,"Gradients_by_loss rec_from_latent_pretrain/: encoder11":0,"Gradients_by_loss recover_latent/: mapper6":0.00724621799298723,"Gradients_by_loss rec_from_latent_pretrain/: mapper15":0,"Gradients_by_loss recover_latent/: mapper0":0.004718969082550829,"Gradients_by_loss rec_from_latent_pretrain/: encoder3":0,"Gradients_by_loss rec_from_latent_pretrain/: mapper6":0,"_step":20,"Gradients_by_loss recover_latent/: mapper15":0.00956108321338893,"Gradients_by_loss recover_latent/: mapper14":0.009941793558053903,"Gradients_by_loss recover_latent/: mapper10":0.009313952687459447,"Gradients_by_loss rec_from_latent_pretrain/: encoder14":0,"important_notes":{"_type":"html-file","sha256":"6a00ca477b0417ed3b405218b57561ec1c077d54657ff085be08c6b302e18085","size":5516,"path":"media/html/important_notes_0_6a00ca477b0417ed3b40.html"},"Gradients_by_loss recover_latent/: encoder13":0.002313542687690786,"Gradients_by_loss rec_from_latent_pretrain/: encoder8":0,"Gradients_by_loss recover_latent/: mapper4":0.007277169077584176,"Gradients_by_loss recover_latent/: mapper3":0.006991904226584544,"Gradients_by_loss recover_latent/: mapper_Sample_id_mapper":0.0028495482201576178,"Gradients_by_loss recover_latent/: encoder6":0.002227256596903315,"Gradients_by_loss recover_latent/: mapper1":0.005595590620651093,"Gradients_by_loss recover_latent/: encoder5":0.0027457547238129995,"Gradients_by_loss rec_from_latent_pretrain/: mapper14":0,"Gradients_by_loss rec_from_latent_pretrain/: mapper13":0,"Gradients_by_loss recover_latent/: encoder10":0.0019713565867217377,"Gradients_by_loss recover_latent/: encoder_pretrain":0.005584403311651983,"Gradients_by_loss recover_latent/: mapper5":0.0071026253092456885,"Gradients_by_loss rec_from_latent_pretrain/: encoder4":0,"Gradients_by_loss recover_latent/: encoder3":0.0034920450267496785,"Gradients_by_loss recover_latent/: mapper8":0.008936252368417429,"Gradients_by_loss rec_from_latent_pretrain/: encoder6":0,"Gradients_by_loss rec_from_latent_pretrain/: encoder0":0,"Gradients_by_loss rec_from_latent_pretrain/: encoder1":0,"Gradients_by_loss rec_from_latent_pretrain/: encoder2":0,"Gradients_by_loss rec_from_latent_pretrain/: encoder9":0,"Gradients_by_loss rec_from_latent_pretrain/: Sample_id_embedder":0,"Gradients_by_loss recover_latent/: encoder7":0.00715211096640549,"Gradients_by_loss recover_latent/: encoder15":0.0004227693413041952,"Gradients_by_loss recover_latent/: encoder4":0.004698155580496287,"Gradients_by_loss recover_latent/: mapper11":0.00927753557004521,"_timestamp":1.7655045735264013e+09,"Gradients_by_loss rec_from_latent_pretrain/: encoder15":0,"Gradients_by_loss rec_from_latent_pretrain/: mapper_Sample_id_mapper":0,"losses/rec_from_latent_pretrain":0.8854279199550892,"Gradients_by_loss rec_from_latent_pretrain/: mapper2":0,"Gradients_by_loss recover_latent/: encoder11":0.0018365916261117378,"Gradients_by_loss recover_latent/: encoder2":0.0038249083440007707,"losses/recover_latent":0.00031009302562371637,"Gradients_by_loss rec_from_latent_pretrain/: encoder12":0,"Gradients_by_loss rec_from_latent_pretrain/: mapper0":0,"Gradients_by_loss recover_latent/: Sample_id_embedder":3.7137102481210604e-05,"Gradients_by_loss rec_from_latent_pretrain/: mapper12":0,"_runtime":187.018529914,"Gradients_by_loss recover_latent/: mapper12":0.009295569099075779,"Gradients_by_loss recover_latent/: mapper7":0.009359732632968432,"Gradients_by_loss rec_from_latent_pretrain/: mapper10":0,"Gradients_by_loss recover_latent/: encoder8":0.0023327410467488393,"Gradients_by_loss rec_from_latent_pretrain/: mapper9":0,"Gradients_by_loss recover_latent/: mapper9":0.008996291317919076,"Gradients_by_loss recover_latent/: encoder9":0.0020129865102409845}